penpen/__init__.py
penpen/prompt_builder.py
penpen/prompt_runner.py
penpen/openai_client/__init__.py
penpen/openai_client/function_handling.py
penpen/openai_client/openai_client.py
penpen/openai_client/openai_client_exceptions.py
PenPen_AI-0.0.11.dist-info/LICENSE
PenPen_AI-0.0.11.dist-info/METADATA
PenPen_AI-0.0.11.dist-info/WHEEL
PenPen_AI-0.0.11.dist-info/entry_points.txt
PenPen_AI-0.0.11.dist-info/top_level.txt
PenPen_AI-0.0.11.dist-info/RECORD
