Metadata-Version: 2.1
Name: PenPen-AI
Version: 0.0.11
Summary: A Python package for standardizing prompts for LLMs.
Home-page: https://github.com/qurami/PenPen
Author: Ufirst S.r.l.
License: MIT
Keywords: LLM,GPT,prompting,ufirst
License-File: LICENSE
Requires-Dist: tiktoken ==0.4.0
Requires-Dist: openai ==0.28.1
